azcam_observe/__init__.py
azcam_observe/__main__.py
azcam_observe/observe_common.py
azcam_observe/observing_script_example.txt
azcam_observe/start.py
azcam_observe/test_script.txt
azcam_observe/observe_cli/__init__.py
azcam_observe/observe_cli/observe_cli.py
azcam_observe/observe_qt/__init__.py
azcam_observe/observe_qt/make_gui.bat
azcam_observe/observe_qt/observe_gui.ui
azcam_observe/observe_qt/observe_gui_ui.py
azcam_observe/observe_qt/observe_qt.py
azcam_observe-22.6.dist-info/entry_points.txt
azcam_observe-22.6.dist-info/LICENSE
azcam_observe-22.6.dist-info/WHEEL
azcam_observe-22.6.dist-info/METADATA
azcam_observe-22.6.dist-info/RECORD
