Metadata-Version: 2.1
Name: azcam-observe
Version: 22.6
Summary: Azcam extension for running observing scripts
Keywords: ccd,imaging,astronomy,sensors
Author: Michael Lesser
Author-email: mlesser@arizona.edu
Requires-Dist: azcam
Requires-Dist: pyside6
Project-URL: Documentation, https://azcam.readthedocs.io/
Project-URL: Repository, https://github.com/mplesser/azcam-observe/
